[{
	"key": "datr",
	"value": "sL9XaCrYWFpK86M9B462_5z9",
	"path": "/",
	"hostOnly": false,
	"domain": ".facebook.com",
	"creation": "2025-07-03T17:51:18.212Z",
	"lastAccessed": "2025-07-03T17:51:18.212Z"
	},
	{
	"key": "sb",
	"value": "sL9XaJtFjuCqnVg3n_lNi5fh",
	"path": "/",
	"hostOnly": false,
	"domain": ".facebook.com",
	"creation": "2025-07-03T17:51:18.212Z",
	"lastAccessed": "2025-07-03T17:51:18.212Z"
	},
	{
	"key": "m_pixel_ratio",
	"value": "2.625",
	"path": "/",
	"hostOnly": false,
	"domain": ".facebook.com",
	"creation": "2025-07-03T17:51:18.212Z",
	"lastAccessed": "2025-07-03T17:51:18.212Z"
	},
	{
	"key": "dpr",
	"value": "2.625",
	"path": "/",
	"hostOnly": false,
	"domain": ".facebook.com",
	"creation": "2025-07-03T17:51:18.212Z",
	"lastAccessed": "2025-07-03T17:51:18.212Z"
	},
	{
	"key": "ps_l",
	"value": "1",
	"path": "/",
	"hostOnly": false,
	"domain": ".facebook.com",
	"creation": "2025-07-03T17:51:18.212Z",
	"lastAccessed": "2025-07-03T17:51:18.212Z"
	},
	{
	"key": "ps_n",
	"value": "1",
	"path": "/",
	"hostOnly": false,
	"domain": ".facebook.com",
	"creation": "2025-07-03T17:51:18.212Z",
	"lastAccessed": "2025-07-03T17:51:18.212Z"
	},
	{
	"key": "vpd",
	"value": "v1%3B749x411x2.625",
	"path": "/",
	"hostOnly": false,
	"domain": ".facebook.com",
	"creation": "2025-07-03T17:51:18.212Z",
	"lastAccessed": "2025-07-03T17:51:18.212Z"
	},
	{
	"key": "x-referer",
	"value": "eyJyIjoiL2NoZWNrcG9pbnQvMTUwMTA5MjgyMzUyNTI4Mi9sb2dvdXQvP25leHQ9aHR0cHMlM0ElMkYlMkZtLmZhY2Vib29rLmNvbSUyRiIsImgiOiIvY2hlY2twb2ludC8xNTAxMDkyODIzNTI1MjgyL2xvZ291dC8%2FbmV4dD1odHRwcyUzQSUyRiUyRm0uZmFjZWJvb2suY29tJTJGIiwicyI6Im0ifQ%3D%3D",
	"path": "/",
	"hostOnly": false,
	"domain": ".facebook.com",
	"creation": "2025-07-03T17:51:18.212Z",
	"lastAccessed": "2025-07-03T17:51:18.212Z"
	},
	{
	"key": "locale",
	"value": "en_GB",
	"path": "/",
	"hostOnly": false,
	"domain": ".facebook.com",
	"creation": "2025-07-03T17:51:18.212Z",
	"lastAccessed": "2025-07-03T17:51:18.212Z"
	},
	{
	"key": "pas",
	"value": "61577311989551%3A9ZkZTvBWfl%2C100088819703826%3Az6c7eUaKfj",
	"path": "/",
	"hostOnly": false,
	"domain": ".facebook.com",
	"creation": "2025-07-03T17:51:18.212Z",
	"lastAccessed": "2025-07-03T17:51:18.212Z"
	},
	{
	"key": "wd",
	"value": "412x892",
	"path": "/",
	"hostOnly": false,
	"domain": ".facebook.com",
	"creation": "2025-07-03T17:51:18.212Z",
	"lastAccessed": "2025-07-03T17:51:18.212Z"
	},
	{
	"key": "c_user",
	"value": "100088819703826",
	"path": "/",
	"hostOnly": false,
	"domain": ".facebook.com",
	"creation": "2025-07-03T17:51:18.212Z",
	"lastAccessed": "2025-07-03T17:51:18.212Z"
	},
	{
	"key": "xs",
	"value": "8%3AYOIz5AobAAVGPQ%3A2%3A1751565050%3A-1%3A-1",
	"path": "/",
	"hostOnly": false,
	"domain": ".facebook.com",
	"creation": "2025-07-03T17:51:18.212Z",
	"lastAccessed": "2025-07-03T17:51:18.212Z"
	},
	{
	"key": "fr",
	"value": "0F1W3EepyTvjaHLkB.AWfPXhu-cmyt8XnPlqbItqRrlVLC8qR-1m2lFE-sLCVrBchWSDw.BoV7-w..AAA.0.0.BoZsL9.AWeVVChPo4vMfU7AJDRLM2tVWME",
	"path": "/",
	"hostOnly": false,
	"domain": ".facebook.com",
	"creation": "2025-07-03T17:51:18.212Z",
	"lastAccessed": "2025-07-03T17:51:18.212Z"
	},
	{
	"key": "fbl_st",
	"value": "100726885%3BT%3A29192750",
	"path": "/",
	"hostOnly": false,
	"domain": ".facebook.com",
	"creation": "2025-07-03T17:51:18.212Z",
	"lastAccessed": "2025-07-03T17:51:18.212Z"
	},
	{
	"key": "wl_cbv",
	"value": "v2%3Bclient_version%3A2858%3Btimestamp%3A1751565053",
	"path": "/",
	"hostOnly": false,
	"domain": ".facebook.com",
	"creation": "2025-07-03T17:51:18.212Z",
	"lastAccessed": "2025-07-03T17:51:18.212Z"
	}]
